rabies/__init__.py
rabies/__version__.py
rabies/boilerplate.py
rabies/parser.py
rabies/run_main.py
rabies/utils.py
rabies/visualization.py
rabies/analysis_pkg/CPCA.py
rabies/analysis_pkg/__init__.py
rabies/analysis_pkg/analysis_functions.py
rabies/analysis_pkg/analysis_math.py
rabies/analysis_pkg/analysis_wf.py
rabies/analysis_pkg/main_wf.py
rabies/analysis_pkg/utils.py
rabies/analysis_pkg/cpca/__init__.py
rabies/analysis_pkg/cpca/modeling.py
rabies/analysis_pkg/cpca/report.py
rabies/analysis_pkg/diagnosis_pkg/__init__.py
rabies/analysis_pkg/diagnosis_pkg/analysis_QC.py
rabies/analysis_pkg/diagnosis_pkg/diagnosis_functions.py
rabies/analysis_pkg/diagnosis_pkg/diagnosis_wf.py
rabies/analysis_pkg/diagnosis_pkg/interfaces.py
rabies/confound_correction_pkg/__init__.py
rabies/confound_correction_pkg/confound_correction.py
rabies/confound_correction_pkg/main_wf.py
rabies/confound_correction_pkg/utils.py
rabies/confound_correction_pkg/mod_ICA_AROMA/ICA_AROMA.py
rabies/confound_correction_pkg/mod_ICA_AROMA/ICA_AROMA_functions.py
rabies/confound_correction_pkg/mod_ICA_AROMA/__init__.py
rabies/confound_correction_pkg/mod_ICA_AROMA/classification_plots.py
rabies/confound_correction_pkg/mod_ICA_AROMA/ica-aroma-via-docker.py
rabies/preprocess_pkg/__init__.py
rabies/preprocess_pkg/bold_main_wf.py
rabies/preprocess_pkg/bold_ref.py
rabies/preprocess_pkg/commonspace_reg.py
rabies/preprocess_pkg/hmc.py
rabies/preprocess_pkg/inho_correction.py
rabies/preprocess_pkg/main_wf copy.py
rabies/preprocess_pkg/main_wf.py
rabies/preprocess_pkg/prep_input.py
rabies/preprocess_pkg/preprocess_visual_QC.py
rabies/preprocess_pkg/registration.py
rabies/preprocess_pkg/resampling.py
rabies/preprocess_pkg/stc.py
rabies/preprocess_pkg/utils.py
rabies-0.5.4.data/scripts/EPI-preprocessing.sh
rabies-0.5.4.data/scripts/antsRegistration_affine_SyN.sh
rabies-0.5.4.data/scripts/ants_generate_iterations.py
rabies-0.5.4.data/scripts/error_check_rabies.py
rabies-0.5.4.data/scripts/gen_DSURQE_masks.py
rabies-0.5.4.dist-info/LICENSE
rabies-0.5.4.dist-info/METADATA
rabies-0.5.4.dist-info/WHEEL
rabies-0.5.4.dist-info/top_level.txt
rabies-0.5.4.dist-info/RECORD
