Metadata-Version: 2.1
Name: rabies
Version: 0.5.4
Summary: RABIES: Rodent Automated Bold Improvement of EPI Sequences.
Home-page: https://github.com/CoBrALab/RABIES
Author: CoBrALab
Author-email: contact@cobralab.ca
License: LICENSE
Platform: UNKNOWN
Classifier: Intended Audience :: Science/Research
Classifier: License :: Free for non-commercial use
Classifier: Programming Language :: Python
Classifier: Programming Language :: Python :: 3
Classifier: Programming Language :: Python :: 3.6
Classifier: Programming Language :: Python :: Implementation :: CPython
Classifier: Programming Language :: Python :: Implementation :: PyPy
Requires-Python: >=3.9.0
Requires-Dist: matplotlib (>=3.3.4)
Requires-Dist: nibabel (>=3.2.1)
Requires-Dist: nilearn (>=0.7.1)
Requires-Dist: nipype (>=1.6.1)
Requires-Dist: numpy (>=1.20.1)
Requires-Dist: pandas (>=1.2.4)
Requires-Dist: pathos (>=0.2.7)
Requires-Dist: pybids (==0.16.3)
Requires-Dist: scikit-learn (>=0.24.1)
Requires-Dist: scipy (>=1.8.1)
Requires-Dist: seaborn (>=0.11.1)
Requires-Dist: simpleitk (==2.0.2)
Requires-Dist: qbatch (==2.3)
Requires-Dist: networkx (<3)
Requires-Dist: traits (<7.0)
